{
  "Routes": [
    {
      "DownstreamHostAndPorts": [
        {
          "Host": "localhost",
          "Port": "44365"
        }
      ],
      "DownstreamPathTemplate": "/api/{version}/customers/{everything}",
      "DownstreamScheme": "https",
      "UpstreamHttpMethod": [ "Get", "Post", "Put", "Delete" ],
      "UpstreamPathTemplate": "/api/{version}/customers/{everything}"
    },
    {
      "DownstreamHostAndPorts": [
        {
          "Host": "localhost",
          "Port": "44365"
        }
      ],
      "DownstreamPathTemplate": "/api/{version}/customers/",
      "DownstreamScheme": "https",
      "UpstreamHttpMethod": [ "Get", "Post", "Put", "Delete" ],
      "UpstreamPathTemplate": "/api/{version}/customers/"
    },
    {
      "DownstreamHostAndPorts": [
        {
          "Host": "localhost",
          "Port": "44388"
        }
      ],
      "DownstreamPathTemplate": "/api/{version}/quote/{everything}",
      "DownstreamScheme": "https",
      "UpstreamHttpMethod": [ "Get", "Post", "Put", "Delete" ],
      "UpstreamPathTemplate": "/api/{version}/quote/{everything}"
    },
    {
      "DownstreamHostAndPorts": [
        {
          "Host": "localhost",
          "Port": "44388"
        }
      ],
      "DownstreamPathTemplate": "/api/{version}/quote/",
      "DownstreamScheme": "https",
      "UpstreamHttpMethod": [ "Get", "Post", "Put", "Delete" ],
      "UpstreamPathTemplate": "/api/{version}/quote/"
    }
  ]
}
